whatismymovie
