Metadata-Version: 1.0
Name: whatismymovie
Version: 0.1.3
Summary: Python API wrapper for whatismymovie.com
Home-page: https://github.com/Pitasi/py-whatismymovie
Author: Antonio Pitasi
Author-email: pitasi.antonio@gmail.com
License: GPL3
Keywords: whatisthismovie imdb api movie
Platform: UNKNOWN
